{
  "tasks": [
    {
      "id": 1742270118018,
      "text": "c",
      "created_at": "18/03/2025 00:55:18",
      "checked": true,
      "finished_at": "18/03/2025 06:55:31"
    },
    {
      "id": 1742292628183,
      "text": "d",
      "created_at": "18/03/2025 07:10:28",
      "checked": true,
      "finished_at": "19/03/2025 19:41:25"
    },
    {
      "id": 1742293048273,
      "text": "faaaaaa",
      "created_at": "18/03/2025 07:17:28",
      "checked": true,
      "finished_at": "19/03/2025 19:41:28"
    },
    {
      "id": 1742293460107,
      "text": "aaaa",
      "created_at": "18/03/2025 07:24:20",
      "checked": false,
      "finished_at": ""
    }
  ]
}